MANIFEST.in
README
distribute_setup.py
setup.py
virtualenvwrapper/__init__.py
virtualenvwrapper/emacs_desktop.py
virtualenvwrapper/emacs_desktop.sh
virtualenvwrapper_emacs_desktop.egg-info/PKG-INFO
virtualenvwrapper_emacs_desktop.egg-info/SOURCES.txt
virtualenvwrapper_emacs_desktop.egg-info/dependency_links.txt
virtualenvwrapper_emacs_desktop.egg-info/entry_points.txt
virtualenvwrapper_emacs_desktop.egg-info/namespace_packages.txt
virtualenvwrapper_emacs_desktop.egg-info/not-zip-safe
virtualenvwrapper_emacs_desktop.egg-info/top_level.txt