Metadata-Version: 1.1
Name: virtualenvwrapper-emacs-desktop
Version: 1.0.1
Summary: virtualenvwrapper plugin to control emacs desktop mode
Home-page: http://www.doughellmann.com/projects/virtualenvwrapper-emacs-desktop/
Author: Doug Hellmann
Author-email: doug.hellmann@gmail.com
License: UNKNOWN
Platform: Any
Classifier: Development Status :: 5 - Production/Stable
Classifier: License :: OSI Approved :: BSD License
Classifier: Programming Language :: Python
Classifier: Intended Audience :: Developers
Classifier: Environment :: Console
Requires: virtualenv
Requires: virtualenvwrapper (>=2.0)
Provides: virtualenvwrapper.emacs_desktop
